ppass/__init__.py
ppass/app.py
ppass/appConfig.py
ppass/modules/folders.py
ppass/modules/git.py
ppass/modules/gpg.py
ppass/modules/params.py
ppass/modules/passwords.py
ppass/modules/rjson.py
ppass/modules/ui.py
ppass/modules/utils.py
ppass/modules/xdotool.py
ppass-1.3.3.dist-info/entry_points.txt
ppass-1.3.3.dist-info/WHEEL
ppass-1.3.3.dist-info/METADATA
ppass-1.3.3.dist-info/RECORD
